opensesame_plugins/media_player_mpy/__init__.py
opensesame_plugins/media_player_mpy/media_player_mpy/__init__.py
opensesame_plugins/media_player_mpy/media_player_mpy/handlers/__init__.py
opensesame_plugins/media_player_mpy/media_player_mpy/handlers/expyriment_handler.py
opensesame_plugins/media_player_mpy/media_player_mpy/handlers/legacy_handler.py
opensesame_plugins/media_player_mpy/media_player_mpy/handlers/opengl_renderer.py
opensesame_plugins/media_player_mpy/media_player_mpy/handlers/psychopy_handler.py
opensesame_plugins/media_player_mpy/media_player_mpy/handlers/pygame_handler.py
opensesame_plugins/media_player_mpy/media_player_mpy/locale/ar/media_player_mpy.md
opensesame_plugins/media_player_mpy/media_player_mpy/locale/ar.qm
opensesame_plugins/media_player_mpy/media_player_mpy/locale/ar.ts
opensesame_plugins/media_player_mpy/media_player_mpy/locale/bn/media_player_mpy.md
opensesame_plugins/media_player_mpy/media_player_mpy/locale/bn.qm
opensesame_plugins/media_player_mpy/media_player_mpy/locale/bn.ts
opensesame_plugins/media_player_mpy/media_player_mpy/locale/de/media_player_mpy.md
opensesame_plugins/media_player_mpy/media_player_mpy/locale/de.qm
opensesame_plugins/media_player_mpy/media_player_mpy/locale/de.ts
opensesame_plugins/media_player_mpy/media_player_mpy/locale/es/media_player_mpy.md
opensesame_plugins/media_player_mpy/media_player_mpy/locale/es.qm
opensesame_plugins/media_player_mpy/media_player_mpy/locale/es.ts
opensesame_plugins/media_player_mpy/media_player_mpy/locale/fr/media_player_mpy.md
opensesame_plugins/media_player_mpy/media_player_mpy/locale/fr.qm
opensesame_plugins/media_player_mpy/media_player_mpy/locale/fr.ts
opensesame_plugins/media_player_mpy/media_player_mpy/locale/he/media_player_mpy.md
opensesame_plugins/media_player_mpy/media_player_mpy/locale/he.qm
opensesame_plugins/media_player_mpy/media_player_mpy/locale/he.ts
opensesame_plugins/media_player_mpy/media_player_mpy/locale/hi/media_player_mpy.md
opensesame_plugin_media_player_mpy-0.2.3.dist-info/METADATA
opensesame_plugin_media_player_mpy-0.2.3.dist-info/WHEEL
opensesame_plugin_media_player_mpy-0.2.3.dist-info/RECORD
