Metadata-Version: 2.3
Name: opensesame-plugin-media_player_mpy
Version: 0.2.3
Summary: A video playback plugin for OpenSesame, based on MoviePy
License: COPYING
Author: Daniel Schreij
Author-email: dschreij@gmail.com
Classifier: License :: Other/Proprietary License
Classifier: Programming Language :: Python :: 2
Classifier: Programming Language :: Python :: 2.7
Classifier: Programming Language :: Python :: 3
Classifier: Programming Language :: Python :: 3.4
Classifier: Programming Language :: Python :: 3.5
Classifier: Programming Language :: Python :: 3.6
Classifier: Programming Language :: Python :: 3.7
Classifier: Programming Language :: Python :: 3.8
Classifier: Programming Language :: Python :: 3.9
Classifier: Programming Language :: Python :: 3.10
Classifier: Programming Language :: Python :: 3.11
Classifier: Programming Language :: Python :: 3.12
Classifier: Programming Language :: Python :: 3.13
Requires-Dist: mediadecoder
Project-URL: Homepage, https://osdoc.cogsci.nl
Project-URL: Repository, https://github.com/open-cogsci/opensesame-plugin-media_player_mpy
